lolpython/__init__.py
lolpython/main.py
lolpython-2.1.0.dist-info/LICENSE
lolpython-2.1.0.dist-info/METADATA
lolpython-2.1.0.dist-info/WHEEL
lolpython-2.1.0.dist-info/entry_points.txt
lolpython-2.1.0.dist-info/top_level.txt
lolpython-2.1.0.dist-info/RECORD
