Metadata-Version: 2.1
Name: lolpython
Version: 2.1.0
Summary: lolcat port of the ruby version
Home-page: https://github.com/Abhishek8394/lol-cat-py
Author: Abhishek8394
Author-email: apbytes@gmail.com
License: GPLv3
Platform: UNKNOWN
